{"id":"1ne2yoYe2BRmHBPYuvZ5a","title":"Bayesian Framework","desc":"","updated":1642037413066,"created":1642037354951,"custom":{},"fname":"science.stats.Bayesian Framework","type":"note","vault":{"fsPath":"vault"},"contentHash":"0ac16aff241c941ded7af65f2fe3163f","links":[{"type":"wiki","from":{"fname":"science.stats.Bayesian Framework","id":"1ne2yoYe2BRmHBPYuvZ5a","vaultName":"vault"},"value":"engineering.technologies.tooling.Pluto","position":{"start":{"line":5,"column":1,"offset":173},"end":{"line":5,"column":43,"offset":215},"indent":[]},"xvault":false,"sameFile":false,"to":{"fname":"engineering.technologies.tooling.Pluto"}},{"from":{"fname":"Philosophy and Rationality.Algorithmic Fairness","id":"74afJvw5CEJWFWkDS8Ri0","vaultName":"vault"},"type":"backlink","position":{"start":{"line":4,"column":77,"offset":109},"end":{"line":4,"column":113,"offset":145},"indent":[]},"value":"science.stats.Bayesian Framework"},{"from":{"fname":"Psychology.Noise (Daniel Kahneman, Oliver Sibony, Cass. R Sunstein)","id":"ie8gb3id450smszhoj11qht","vaultName":"vault"},"type":"backlink","position":{"start":{"line":142,"column":1,"offset":3761},"end":{"line":142,"column":37,"offset":3797},"indent":[]},"value":"science.stats.Bayesian Framework"},{"from":{"fname":"science.CS.theory.Code Transformations.Differentiable Programming.pymc3","id":"39UBkcDOQ6LeYYG1tabGB","vaultName":"vault"},"type":"backlink","position":{"start":{"line":5,"column":1,"offset":101},"end":{"line":5,"column":37,"offset":137},"indent":[]},"value":"science.stats.Bayesian Framework"}],"anchors":{},"children":[],"parent":"DrDDAM98fbdfBEotQX5EQ","data":{},"schema":{"schemaId":"ruyvpn5bngeinwshxuy7y19","moduleId":"science"}}
