{"id":"74afJvw5CEJWFWkDS8Ri0","title":"Algorithmic Fairness","desc":"","updated":1642426730441,"created":1642360362865,"custom":{},"fname":"Philosophy and Rationality.Algorithmic Fairness","type":"note","vault":{"fsPath":"vault"},"contentHash":"25e474c8720c053046f1932f2acae456","links":[{"type":"wiki","from":{"fname":"Philosophy and Rationality.Algorithmic Fairness","id":"74afJvw5CEJWFWkDS8Ri0","vaultName":"vault"},"value":"science.stats.Bayesian Framework","position":{"start":{"line":4,"column":77,"offset":109},"end":{"line":4,"column":113,"offset":145},"indent":[]},"xvault":false,"sameFile":false,"to":{"fname":"science.stats.Bayesian Framework"}},{"from":{"fname":"engineering.system_design.ML System Design.Recommender Systems","id":"QE1BddXlccbyYN1avaB4M","vaultName":"vault"},"type":"backlink","position":{"start":{"line":233,"column":1,"offset":5922},"end":{"line":233,"column":52,"offset":5973},"indent":[]},"value":"Philosophy and Rationality.Algorithmic Fairness"},{"from":{"fname":"engineering.system_design.ML System Design.Recommender Systems","id":"QE1BddXlccbyYN1avaB4M","vaultName":"vault"},"type":"backlink","position":{"start":{"line":236,"column":1,"offset":6006},"end":{"line":236,"column":75,"offset":6080},"indent":[]},"value":"Philosophy and Rationality.Algorithmic Fairness"}],"anchors":{"error-is-same-across-groups":{"type":"header","text":"Error is same across groups","value":"error-is-same-across-groups","line":9,"column":0,"depth":2},"independence":{"type":"header","text":"Independence","value":"independence","line":14,"column":0,"depth":1},"^independence-formula":{"type":"block","value":"independence-formula","line":19,"column":115}},"children":[],"parent":"vB321AipYCs6ldVC0APs9","data":{}}
