{"id":"BxrMQntKAmf0chh426nZD","title":"Matrix Chain Multiplication Algorithm","desc":"","updated":1641825592001,"created":1641824235344,"custom":{},"fname":"science.CS.algos.matrixChainMultiplication","type":"note","vault":{"fsPath":"vault"},"contentHash":"3341db35032ddcde59a52c363e05581b","links":[{"type":"wiki","from":{"fname":"science.CS.algos.matrixChainMultiplication","id":"BxrMQntKAmf0chh426nZD","vaultName":"vault"},"value":"science.CS.algos.dynamicProgramming","position":{"start":{"line":3,"column":1,"offset":75},"end":{"line":3,"column":40,"offset":114},"indent":[]},"xvault":false,"sameFile":false,"to":{"fname":"science.CS.algos.dynamicProgramming"}},{"type":"wiki","from":{"fname":"science.CS.algos.matrixChainMultiplication","id":"BxrMQntKAmf0chh426nZD","vaultName":"vault"},"value":"science.CS.algos.StrassenAlgorithm","position":{"start":{"line":9,"column":11,"offset":368},"end":{"line":9,"column":49,"offset":406},"indent":[]},"xvault":false,"sameFile":false,"to":{"fname":"science.CS.algos.StrassenAlgorithm"}},{"from":{"fname":"science.math.Linear Algebra","id":"F4qDUpHVv34wdYvQu0h2O","vaultName":"vault"},"type":"backlink","position":{"start":{"line":36,"column":1,"offset":794},"end":{"line":36,"column":47,"offset":840},"indent":[]},"value":"science.CS.algos.matrixChainMultiplication"},{"from":{"fname":"science.CS.algos.dynamicProgramming","id":"s8P64cXaxlGWXzSWnpGjP","vaultName":"vault"},"type":"backlink","position":{"start":{"line":139,"column":1,"offset":3859},"end":{"line":139,"column":47,"offset":3905},"indent":[]},"value":"science.CS.algos.matrixChainMultiplication"}],"anchors":{"a-little-bit-of-a-tricky-problem-insofar-as-dynamic-programming-goes":{"type":"header","text":"A little bit of a tricky problem insofar as dynamic programming goes.","value":"a-little-bit-of-a-tricky-problem-insofar-as-dynamic-programming-goes","line":7,"column":0,"depth":3}},"children":[],"parent":"R3N3tS0RNCjMvqnqSnGZI","data":{}}
