{"id":"s8nfdbk3pt5crhn7l7b2dsp","title":"Master Theorem of Algorithmic Complexity","desc":"","updated":1659207017294,"created":1659207017294,"custom":{},"fname":"science.CS.algos.Master Theorem of Algorithmic Complexity","type":"note","vault":{"fsPath":"vault"},"contentHash":"c675a5bf83e62d55f7af1a0da3581028","links":[{"from":{"fname":"algos.Discrete Fourier Transform","id":"j5ccfw6oz7ry5c5rc3gqtlf","vaultName":"vault"},"type":"backlink","position":{"start":{"line":52,"column":13,"offset":1691},"end":{"line":52,"column":74,"offset":1752},"indent":[]},"value":"science.CS.algos.Master Theorem of Algorithmic Complexity"}],"anchors":{},"children":[],"parent":"R3N3tS0RNCjMvqnqSnGZI","data":{}}
