{"id":"zXkhM0rQ06UlUWNPLSODK","title":"SVD","desc":"","updated":1642351269786,"created":1641866189369,"custom":{},"fname":"science.stats.Dimensionality Reduction.SVD","type":"note","vault":{"fsPath":"vault"},"contentHash":"96aa789b6f03caf9a3948efcfe8451e7","links":[{"type":"wiki","from":{"fname":"science.stats.Dimensionality Reduction.SVD","id":"zXkhM0rQ06UlUWNPLSODK","vaultName":"vault"},"value":"science.math.Linear Algebra.Singular Value Decomposition","position":{"start":{"line":1,"column":1,"offset":0},"end":{"line":1,"column":61,"offset":60},"indent":[]},"xvault":false,"sameFile":false,"to":{"fname":"science.math.Linear Algebra.Singular Value Decomposition"}},{"type":"wiki","from":{"fname":"science.stats.Dimensionality Reduction.SVD","id":"zXkhM0rQ06UlUWNPLSODK","vaultName":"vault"},"value":"science.math.Linear Algebra","position":{"start":{"line":9,"column":1,"offset":229},"end":{"line":9,"column":37,"offset":265},"indent":[]},"xvault":false,"sameFile":false,"to":{"fname":"science.math.Linear Algebra","anchorHeader":"^pca"}},{"from":{"fname":"science.math.Linear Algebra","id":"F4qDUpHVv34wdYvQu0h2O","vaultName":"vault"},"type":"backlink","position":{"start":{"line":92,"column":1,"offset":2550},"end":{"line":92,"column":47,"offset":2596},"indent":[]},"value":"science.stats.Dimensionality Reduction.SVD"},{"from":{"fname":"science.math.Linear Algebra.Matrix Decompositions","id":"AVYoVPSXLVOOeTyZ4cA5e","vaultName":"vault"},"type":"backlink","position":{"start":{"line":6,"column":1,"offset":64},"end":{"line":6,"column":47,"offset":110},"indent":[]},"value":"science.stats.Dimensionality Reduction.SVD"}],"anchors":{"fast-r-library":{"type":"header","text":"Fast R library","value":"fast-r-library","line":10,"column":0,"depth":1}},"children":[],"parent":"S3Pb07yFFEB8AEEPvM1GK","data":{}}
